README
setup.cfg
setup.py
passta/__init__.py
passta/clipboard.py
passta/gpg.py
passta/store.py
passta/testcases.py
passta.egg-info/PKG-INFO
passta.egg-info/SOURCES.txt
passta.egg-info/dependency_links.txt
passta.egg-info/entry_points.txt
passta.egg-info/requires.txt
passta.egg-info/top_level.txt
passta/cli/__init__.py
passta/cli/get.py
passta/cli/list.py
passta/cli/main.py
passta/cli/remove.py
passta/cli/store.py