Metadata-Version: 1.1
Name: passta
Version: 1.3
Summary: simple password manager
Home-page: http://github.com/natano/passta/
Author: Martin Natano
Author-email: natano@natano.net
License: ISC
Keywords: Password,Safe,Simple,GPG
Platform: UNKNOWN
Classifier: Intended Audience :: End Users/Desktop
Classifier: Intended Audience :: System Administrators
Classifier: License :: OSI Approved :: ISC License (ISCL)
Classifier: Programming Language :: Python
Classifier: Programming Language :: Python :: 3
Classifier: Programming Language :: Python :: 3.2
Classifier: Programming Language :: Python :: 3.3
Classifier: Topic :: Utilities
Classifier: Development Status :: 5 - Production/Stable
